<?xml version="1.0" ?>
<sfc zoom="0.90909094" canvas="10 14" execution-mode="Callable" version="7.9.0 (b2016101208)" timestamp="Mon May 01 15:37:17 CDT 2017" hot-editable="false" persist-state="true">
	<oncancel>def onCancel(chart):
	"""
	This will run once if the chart is cancelled.

	Arguments:
		chart: A reference to the chart's scope.
	"""
	from xom.vistalon.sfc.polmerizeEpdm.rateChange.transfer import abortHandler
	abortHandler(chart,block)</oncancel>
	<onabort>def onAbort(chart):
	"""
	This will run once if the chart is aborted.
	The exception that caused the abort is
	available via chart.abortCause

	Arguments:
		chart: A reference to the chart's scope.
	"""
	from xom.vistalon.sfc.polmerizeEpdm.rateChange.transfer import abortHandler
	abortHandler(chart,block)</onabort>
	<step id="83e34b9b-5f31-11dd-97b9-00142223a71b" location="1 1" name="Begin" factory-id="begin-step">		<associated-data>{}</associated-data>
	</step>
	<step id="83e34b1a-5f31-11dd-97b9-00142223a71b" location="1 2" name="SetCtrlrModes" factory-id="com.ils.manualDataEntryStep"><manualDataConfig>{"rows":[{"key":"RC-MAIN-C3-C2-RATIO-MODE.VALUE","destination":"operation","prompt":"Set Main C3/C2 Ratio Mode to AUTO","units":"","defaultValue":"AUTO","lowLimit":null,"highLimit":null},{"key":"RC-SEC-C3-C2-RATIO-MODE.VALUE","destination":"operation","prompt":"Set Sec C3/c2 Ratio Mode to AUTO","units":"","defaultValue":"AUTO","lowLimit":null,"highLimit":null},{"key":"RC-MAIN-C9-C2-RATIO-MODE.VALUE","destination":"operation","prompt":"Set Main C9/C2 Ratio Mode to AUTO","units":"","defaultValue":"AUTO","lowLimit":null,"highLimit":null},{"key":"RC-SEC-C9-C2-RATIO-MODE.VALUE","destination":"operation","prompt":"Set Sec C9/C2 Ratio Mode to AUTO","units":"","defaultValue":"AUTO","lowLimit":null,"highLimit":null}]}</manualDataConfig><description></description><scale>1.0</scale><timeoutUnit>SEC</timeoutUnit><windowTitle></windowTitle><timeout>-1.0</timeout><buttonLabel></buttonLabel><name>SetCtrlrModes</name><id>83e34b1a-5f31-11dd-97b9-00142223a71b</id><position>topCenter</position><window>S88-MANUAL-DATA-ENTRY-TASK-DIALOG</window><requireAllInputs>true</requireAllInputs><autoMode>automatic</autoMode>		<associated-data>{}</associated-data>
	</step>
	<step id="83e34ae4-5f31-11dd-97b9-00142223a71b" location="1 3" name="WriteModesforRateChange" factory-id="com.ils.writeOutputStep"><globalErrorCountKey></globalErrorCountKey><timerKey>rc-timer</timerKey><timerLocation>operation</timerLocation><recipeLocation>operation</recipeLocation><timerSet>false</timerSet><description></description><globalErrorCountLocation>local</globalErrorCountLocation><verbose>true</verbose><name>WriteModesforRateChange</name><writeOutputConfig>{"rows":[{"key":"RC-MAIN-C3-C2-RATIO-MODE","confirmWrite":true},{"key":"RC-SEC-C3-C2-RATIO-MODE","confirmWrite":true},{"key":"RC-MAIN-C9-C2-RATIO-MODE","confirmWrite":true},{"key":"RC-SEC-C9-C2-RATIO-MODE","confirmWrite":true}]}</writeOutputConfig><id>83e34ae4-5f31-11dd-97b9-00142223a71b</id>		<associated-data>{}</associated-data>
	</step>
	<step id="83e34b1d-5f31-11dd-97b9-00142223a71b" location="1 5" name="TransferTrueMsg" factory-id="com.ils.controlPanelMessageStep"><description></description><timeoutUnit>SEC</timeoutUnit><message>Transfer of rate change setpoints to the setpoint download screen has been selected by the operator.</message><priority>Info</priority><postToQueue>false</postToQueue><timeout>10.0</timeout><ackRequired>false</ackRequired><name>TransferTrueMsg</name><id>83e34b1d-5f31-11dd-97b9-00142223a71b</id>		<associated-data>{}</associated-data>
	</step>
	<step id="83e34b6f-5f31-11dd-97b9-00142223a71b" location="1 6" name="TransferData" factory-id="action-step">
		<start-script>def onStart(chart,block):
	from xom.vistalon.sfc.polmerizeEpdm.rateChange.transfer import transfer
	transfer(chart,block)</start-script>
		<associated-data>{}</associated-data>
	</step>
	<step id="83e34b2c-5f31-11dd-97b9-00142223a71b" location="1 7" name="CheckForspWorkspace" factory-id="enclosing-step" chart-path="VistalonUnitProcedure/PolymerizeEpdm/RateChange/CheckForSpWorkspace" execution-mode="RunUntilCompletion">		<associated-data>{}</associated-data>
	</step>
	<step id="83e34b21-5f31-11dd-97b9-00142223a71b" location="1 8" name="ResetCtlrmodes" factory-id="com.ils.manualDataEntryStep"><manualDataConfig>{"rows":[{"key":"RC-MAIN-C3-C2-RATIO-MODE.VALUE","destination":"operation","prompt":"Set Main C3/C2 Ratio Mode to CAS","units":"","defaultValue":"CAS","lowLimit":null,"highLimit":null},{"key":"RC-SEC-C3-C2-RATIO-MODE.VALUE","destination":"operation","prompt":"Set Sec C3/C2 Ratio Mode to CAS","units":"","defaultValue":"CAS","lowLimit":null,"highLimit":null},{"key":"RC-MAIN-C9-C2-RATIO-MODE.VALUE","destination":"operation","prompt":"Set Main C9/C2 Ratio Mode to CAS","units":"","defaultValue":"CAS","lowLimit":null,"highLimit":null},{"key":"RC-SEC-C9-C2-RATIO-MODE.VALUE","destination":"operation","prompt":"Set Sec C9/C2 Ratio Mode to CAS","units":"","defaultValue":"CAS","lowLimit":null,"highLimit":null}]}</manualDataConfig><description></description><scale>1.0</scale><timeoutUnit>SEC</timeoutUnit><windowTitle></windowTitle><timeout>-1.0</timeout><buttonLabel></buttonLabel><name>ResetCtlrmodes</name><id>83e34b21-5f31-11dd-97b9-00142223a71b</id><position>topCenter</position><window>S88-MANUAL-DATA-ENTRY-TASK-DIALOG</window><requireAllInputs>true</requireAllInputs><autoMode>automatic</autoMode>		<associated-data>{}</associated-data>
	</step>
	<step id="83e34b26-5f31-11dd-97b9-00142223a71b" location="1 9" name="ReWritectlrModes" factory-id="com.ils.writeOutputStep"><globalErrorCountKey></globalErrorCountKey><timerKey>rc-timer</timerKey><timerLocation>operation</timerLocation><recipeLocation>operation</recipeLocation><timerSet>false</timerSet><description></description><globalErrorCountLocation>local</globalErrorCountLocation><verbose>true</verbose><name>ReWritectlrModes</name><writeOutputConfig>{"rows":[{"key":"RC-MAIN-C3-C2-RATIO-MODE","confirmWrite":true},{"key":"RC-SEC-C3-C2-RATIO-MODE","confirmWrite":true},{"key":"RC-MAIN-C9-C2-RATIO-MODE","confirmWrite":true},{"key":"RC-SEC-C9-C2-RATIO-MODE","confirmWrite":true}]}</writeOutputConfig><id>83e34b26-5f31-11dd-97b9-00142223a71b</id>		<associated-data>{}</associated-data>
	</step>
	<step id="83e34b73-5f31-11dd-97b9-00142223a71b" location="1 11" name="End" factory-id="end-step">		<associated-data>{}</associated-data>
	</step>
	<transition id="f211b730-2029-4bcd-835a-9781554c7adf" location="1 4">{previous.workDone}</transition>
	<transition id="9b151dd3-486e-44d8-81ef-2657cbb01885" location="1 10">{previous.workDone}</transition>
	<note id="cea708b1-7963-4c6e-bc47-543d8d078aa0" location="3 0" size="3 1">This chart has an Abort handler.</note>

</sfc>
